catalyseur/__init__.py
catalyseur-0.0.22.dist-info/METADATA
catalyseur-0.0.22.dist-info/RECORD
catalyseur-0.0.22.dist-info/WHEEL
catalyseur-0.0.22.dist-info/top_level.txt
